custodes/__init__.py
custodes/auth.py
custodes/client.py
custodes/config.py
custodes/server.py
tests/__init__.py
tests/test_client.py
tests/test_server.py
custodes-0.1.1.dist-info/METADATA
custodes-0.1.1.dist-info/WHEEL
custodes-0.1.1.dist-info/top_level.txt
custodes-0.1.1.dist-info/RECORD
