Metadata-Version: 2.1
Name: custodes
Version: 0.1.1
Summary: ok
Home-page: https://github.com/private_repo/uuidentifier
Author: aldf
Author-email: dafiosl@gmail.com
Classifier: Programming Language :: Python :: 3
Classifier: License :: OSI Approved :: MIT License
Classifier: Operating System :: OS Independent
Requires-Dist: aiohttp
Requires-Dist: rich
Requires-Dist: simauth
Requires-Dist: aio-pika
Requires-Dist: urllib3
Requires-Dist: python-dotenv
